{
  "questions": [
    { 
      "question": "What's your favorite color?",
      "choices":[
        "Green",
        "Teal",
        "Blue",
        "Orange",
        "Pink",
        "Purple"
      ]
    },
    { 
      "question": "What's your favorite season?",
      "choices":[
        "Winter",
        "Spring",
        "Summer",
        "Fall"
      ]
    },
    { 
      "question": "What do you do at parties?",
      "choices":[
        "Bring food for everyone",
        "Play DJ, I bring the music",
        "I make friends with the house pets",
        "I take selfies and make sure everyone knows i'm there",
        "I jump into party games",
        "I try to start a conversation with someone"
      ]
    }
  ]
}